CHANGES.rst
FAQ
LICENSE
MANIFEST.in
Makefile
README.rst
common.mk
mocks.options
rules.mk
setup.py
theory.options
Corrfunc/__init__.py
Corrfunc/io.py
Corrfunc/utils.py
Corrfunc.egg-info/PKG-INFO
Corrfunc.egg-info/SOURCES.txt
Corrfunc.egg-info/dependency_links.txt
Corrfunc.egg-info/not-zip-safe
Corrfunc.egg-info/requires.txt
Corrfunc.egg-info/top_level.txt
Corrfunc/../mocks/tests/Mr19_mock.DD
Corrfunc/../mocks/tests/Mr19_mock.DR
Corrfunc/../mocks/tests/Mr19_mock_DDsmu.DR
Corrfunc/../mocks/tests/Mr19_mock_DDsmu.RR
Corrfunc/../mocks/tests/Mr19_mock_vpf
Corrfunc/../mocks/tests/Mr19_mock_wtheta.DD
Corrfunc/../mocks/tests/Mr19_mock_wtheta.DR
Corrfunc/../mocks/tests/Mr19_randoms_vpf
Corrfunc/../mocks/tests/angular_bins
Corrfunc/../mocks/tests/bins
Corrfunc/../mocks/tests/data/Mr19_centers_xyz_forVPF_rmax_10Mpc.txt
Corrfunc/../mocks/tests/data/Mr19_mock_northonly.rdcz.dat
Corrfunc/../mocks/tests/data/Mr19_mock_northonly.rdcz.ff
Corrfunc/../mocks/tests/data/Mr19_randoms_northonly.rdcz.ff
Corrfunc/../theory/tests/Mr19_DD_nonperiodic
Corrfunc/../theory/tests/Mr19_DD_periodic
Corrfunc/../theory/tests/Mr19_DDrppi_nonperiodic
Corrfunc/../theory/tests/Mr19_DDrppi_periodic
Corrfunc/../theory/tests/Mr19_DDsmu_nonperiodic
Corrfunc/../theory/tests/Mr19_DDsmu_periodic
Corrfunc/../theory/tests/Mr19_vpf_periodic
Corrfunc/../theory/tests/Mr19_wp
Corrfunc/../theory/tests/Mr19_xi
Corrfunc/../theory/tests/bins
Corrfunc/../theory/tests/cmass_DD_periodic
Corrfunc/../theory/tests/cmass_DR_nonperiodic
Corrfunc/../theory/tests/cmass_DR_periodic
Corrfunc/../theory/tests/cmass_RR_periodic
Corrfunc/../theory/tests/data/cmassmock_Zspace.ff
Corrfunc/../theory/tests/data/gals_Mr19.ff
Corrfunc/../theory/tests/data/random_Zspace.ff
Corrfunc/mocks/DDrppi_mocks.py
Corrfunc/mocks/DDsmu_mocks.py
Corrfunc/mocks/DDtheta_mocks.py
Corrfunc/mocks/__init__.py
Corrfunc/mocks/vpf_mocks.py
Corrfunc/tests/__init__.py
Corrfunc/tests/common.py
Corrfunc/tests/test_mocks.py
Corrfunc/tests/test_theory.py
Corrfunc/theory/DD.py
Corrfunc/theory/DDrppi.py
Corrfunc/theory/DDsmu.py
Corrfunc/theory/__init__.py
Corrfunc/theory/vpf.py
Corrfunc/theory/wp.py
Corrfunc/theory/xi.py
docs/source/all-interfaces.rst
