Metadata-Version: 2.1
Name: Corrfunc
Version: 2.5.3
Summary: Blazing fast correlation functions on the CPU
Home-page: https://github.com/manodeep/Corrfunc
Download-URL: https://github.com/manodeep/Corrfunc/archive/Corrfunc-2.5.3.tar.gz
Author: Manodeep Sinha
Author-email: manodeep@gmail.com
Maintainer: Manodeep Sinha
Maintainer-email: manodeep@gmail.com
License: MIT
Keywords: correlation functions,simulations,surveys,galaxies
Platform: Linux
Platform: Mac OSX
Platform: Unix
Classifier: Development Status :: 4 - Beta
Classifier: Intended Audience :: Developers
Classifier: Intended Audience :: Science/Research
Classifier: License :: OSI Approved :: MIT License
Classifier: Natural Language :: English
Classifier: Operating System :: POSIX
Classifier: Programming Language :: C
Classifier: Programming Language :: Python
Classifier: Programming Language :: Python :: 2
Classifier: Programming Language :: Python :: 2.7
Classifier: Programming Language :: Python :: 3
Classifier: Programming Language :: Python :: 3.7
Classifier: Programming Language :: Python :: 3.8
Classifier: Programming Language :: Python :: 3.9
Classifier: Programming Language :: Python :: 3.10
Provides: Corrfunc
Requires-Python: >=2.7,!=3.0.*, !=3.1.*, !=3.2.*, !=3.3.*, !=3.4.*, !=3.5.*, !=3.6.*, <4
License-File: LICENSE
Requires-Dist: numpy>=1.20
Requires-Dist: future
Requires-Dist: wurlitzer
